tiktor/__init__.py
tiktor/main.py
tiktor-1.0.0.dist-info/METADATA
tiktor-1.0.0.dist-info/WHEEL
tiktor-1.0.0.dist-info/entry_points.txt
tiktor-1.0.0.dist-info/top_level.txt
tiktor-1.0.0.dist-info/RECORD
