Metadata-Version: 2.4
Name: TikTor
Version: 1.0.0
Summary: TikTok Downloader tool (TikTor)
Home-page: https://github.com/ccxos/TikTor
Author: oil point
Author-email: alrabayryn018@gmail.com
License: MIT
Classifier: Programming Language :: Python :: 3
Classifier: License :: OSI Approved :: MIT License
Classifier: Operating System :: OS Independent
Requires-Python: >=3.8
Requires-Dist: requests
Requires-Dist: pycountry
Dynamic: description
Dynamic: description-content-type
Dynamic: requires-dist
